allin1/__about__.py
allin1/__init__.py
allin1/analyze.py
allin1/cli.py
allin1/config.py
allin1/demix.py
allin1/helpers.py
allin1/py.typed
allin1/sonify.py
allin1/spectrogram.py
allin1/typings.py
allin1/utils.py
allin1/visualize.py
allin1/models/__init__.py
allin1/models/allinone.py
allin1/models/dinat.py
allin1/models/ensemble.py
allin1/models/loaders.py
allin1/models/utils.py
allin1/postprocessing/__init__.py
allin1/postprocessing/functional.py
allin1/postprocessing/helpers.py
allin1/postprocessing/metrical.py
allin1/postprocessing/tempo.py
allin1/training/__init__.py
allin1/training/evaluate.py
allin1/training/helpers.py
allin1/training/preprocess.py
allin1/training/train.py
allin1/training/trainer.py
allin1/training/data/__init__.py
allin1/training/data/utils.py
allin1/training/data/datasets/__init__.py
allin1/training/data/datasets/collate.py
allin1/training/data/datasets/datasetbase.py
allin1/training/data/datasets/harmonix/__init__.py
allin1/training/data/datasets/harmonix/datamodule.py
allin1/training/data/datasets/harmonix/dataset.py
allin1/training/data/eventconverters/__init__.py
allin1/training/data/eventconverters/datasetconverters.py
allin1/training/data/eventconverters/eventconverters.py
allin1-1.1.0.dist-info/METADATA
allin1-1.1.0.dist-info/WHEEL
allin1-1.1.0.dist-info/entry_points.txt
allin1-1.1.0.dist-info/licenses/LICENSE
allin1-1.1.0.dist-info/RECORD
