Metadata-Version: 2.1
Name: allin1
Version: 1.1.0
Summary: All-In-One Music Structure Analyzer
Project-URL: Documentation, https://github.com/mir-aidj/all-in-one#readme
Project-URL: Issues, https://github.com/mir-aidj/all-in-one/issues
Project-URL: Source, https://github.com/mir-aidj/all-in-one
Author-email: Taejun Kim <taejun@kaist.ac.kr>
License-Expression: MIT
License-File: LICENSE
Keywords: allin1,analysis,beat,downbeat,music,structure,tracking
Classifier: Development Status :: 5 - Production/Stable
Classifier: Programming Language :: Python
Classifier: Programming Language :: Python :: 3.8
Classifier: Programming Language :: Python :: 3.9
Classifier: Programming Language :: Python :: 3.10
Classifier: Programming Language :: Python :: 3.11
Classifier: Programming Language :: Python :: Implementation :: CPython
Classifier: Programming Language :: Python :: Implementation :: PyPy
Requires-Python: >=3.8
Requires-Dist: demucs
Requires-Dist: huggingface-hub
Requires-Dist: hydra-core
Requires-Dist: librosa
Requires-Dist: matplotlib
Requires-Dist: natten; platform_system == 'Darwin'
Requires-Dist: numpy
Requires-Dist: omegaconf
Provides-Extra: train
Requires-Dist: lightning; extra == 'train'
Requires-Dist: mir-eval; extra == 'train'
Requires-Dist: numpy<1.24; extra == 'train'
Requires-Dist: timm; extra == 'train'
Requires-Dist: wandb; extra == 'train'
